xler8/__init__.py
xler8/__main__.py
xler8/csd/__init__.py
xler8/csd/__main__.py
xler8/csv2xlsx/__init__.py
xler8/csv2xlsx/simple/__init__.py
xler8/csv2xlsx/simple/__main__.py
xler8/diff/__init__.py
xler8/diff/__main__.py
xler8/dmaker/__init__.py
xler8/dmaker/__main__.py
xler8/match/__init__.py
xler8/match/__main__.py
xler8/matrixtranspose/__init__.py
xler8/matrixtranspose/__main__.py
xler8/newdivide/__init__.py
xler8/newdivide/__main__.py
xler8/text/__init__.py
xler8/text/__main__.py
xler8/text/tsvmaker/__init__.py
xler8/text/tsvmaker/__main__.py
xler8/vba/__init__.py
xler8/vba/__main__.py
xler8/vbastatic/__init__.py
xler8/vbastatic/__main__.py
xler8/work/__init__.py
xler8/work/__main__.py
xler8/xcolcat/__init__.py
xler8/xcolcat/__main__.py
xler8/xhdrcat/__init__.py
xler8/xhdrcat/__main__.py
xler8/xsd/__init__.py
xler8/xsd/__main__.py
xler8-0.41.1.dist-info/licenses/LICENSE
xler8-0.41.1.dist-info/METADATA
xler8-0.41.1.dist-info/WHEEL
xler8-0.41.1.dist-info/top_level.txt
xler8-0.41.1.dist-info/RECORD
